{
  "FMG_ID": 201,
  "Entries": [
    {
      "Text": "Use selected item",
      "IDList": [
        4100
      ]
    },
    {
      "Text": "Leave selected item here",
      "IDList": [
        4101
      ]
    },
    {
      "Text": "Discard selected item",
      "IDList": [
        4102
      ]
    },
    {
      "Text": "%null%",
      "IDList": [
        4103,
        4104,
        4105,
        4106,
        4107,
        4108,
        4109,
        4113,
        4114,
        4115,
        4116,
        4117,
        4118,
        4119,
        4120,
        5103,
        110008,
        110011,
        110012,
        110013,
        110014,
        110015,
        110016,
        110017,
        110018,
        110019,
        110108,
        110109,
        110110,
        110111,
        110112,
        110113,
        110114,
        110115,
        110116,
        110203,
        110204,
        110205,
        110206,
        110207,
        110208,
        111007,
        111008,
        111009,
        111012,
        111013,
        111014,
        111015,
        111016,
        111017,
        111018,
        111019,
        111021,
        221001,
        221002,
        221003,
        221004,
        221005,
        221006,
        221007,
        221008,
        221009,
        280006,
        280007,
        280008,
        280009,
        280010,
        291004,
        291005,
        291006,
        291007,
        291008,
        291009,
        291012,
        291013,
        291014,
        291015,
        291016,
        291017,
        291018,
        291019,
        291024,
        291026,
        291027,
        291028,
        291029,
        292002,
        292003,
        292004,
        292005,
        292006,
        292007,
        292008,
        292009,
        292014,
        292015,
        292016,
        292017,
        292018,
        292019,
        292021,
        292022,
        292023,
        292024,
        292026,
        292027,
        292028,
        292029,
        292031,
        292032,
        292033,
        292034,
        292035,
        292036,
        292037,
        292038,
        292039,
        292041,
        292042,
        292043,
        292044,
        292045,
        292046,
        292047,
        292048,
        292049,
        292051,
        292052,
        292053,
        292054,
        292055,
        292056,
        292057,
        292058,
        292059,
        292065,
        292066,
        292067,
        292068,
        292069,
        292073,
        292074,
        292075,
        292076,
        292077,
        292078,
        292079,
        293004,
        293005,
        293006,
        293007,
        293008,
        293009,
        293105,
        293106,
        293107,
        293108,
        293109,
        293115,
        293116,
        293117,
        293118,
        293119,
        293126,
        293127,
        293128,
        293129,
        293132,
        293133,
        293134,
        293135,
        293136,
        293137,
        293138,
        293139,
        293146,
        293147,
        293148,
        293149,
        293157,
        293158,
        293159,
        293174,
        293175,
        293176,
        293177,
        293178,
        293179,
        293183,
        293184,
        293185,
        293186,
        293187,
        293188,
        293189,
        297102,
        297103,
        297104,
        297105,
        297106,
        297107,
        297108,
        297109,
        297113,
        297114,
        297115,
        297116,
        297117,
        297118,
        297119,
        297123,
        297124,
        297128,
        297129,
        297140,
        297141,
        297142,
        297143,
        297144,
        297145,
        297146,
        297147,
        297148,
        297149,
        297155,
        297161,
        297162,
        297163,
        297164,
        297165,
        297166,
        297167,
        297168,
        297169,
        297172,
        297173,
        297174,
        297175,
        297176,
        297177,
        297178,
        297179,
        297182,
        297183,
        297184
      ]
    },
    {
      "Text": "Use selected items",
      "IDList": [
        4110
      ]
    },
    {
      "Text": "Leave selected items here",
      "IDList": [
        4111
      ]
    },
    {
      "Text": "Discard selected items ",
      "IDList": [
        4112
      ]
    },
    {
      "Text": "Select items to leave here",
      "IDList": [
        4121
      ]
    },
    {
      "Text": "Select items to discard",
      "IDList": [
        4122
      ]
    },
    {
      "Text": "Use selected number of items",
      "IDList": [
        5100
      ]
    },
    {
      "Text": "Leave selected number of items here",
      "IDList": [
        5101
      ]
    },
    {
      "Text": "Discard selected number of items",
      "IDList": [
        5102
      ]
    },
    {
      "Text": "Purchase selected number of items",
      "IDList": [
        5104
      ]
    },
    {
      "Text": "Sell selected number of items",
      "IDList": [
        5105
      ]
    },
    {
      "Text": "Store selected number of items",
      "IDList": [
        5106
      ]
    },
    {
      "Text": "Take out selected number of items",
      "IDList": [
        5107
      ]
    },
    {
      "Text": "Select a sorting method",
      "IDList": [
        6000
      ]
    },
    {
      "Text": "Select entry to check",
      "IDList": [
        30000
      ]
    },
    {
      "Text": "Confirm settings and continue",
      "IDList": [
        40331
      ]
    },
    {
      "Text": "Restore default settings",
      "IDList": [
        40500
      ]
    },
    {
      "Text": "Select an item to interact with",
      "IDList": [
        102000
      ]
    },
    {
      "Text": "Select slot to equip",
      "IDList": [
        103000
      ]
    },
    {
      "Text": "Select item to equip",
      "IDList": [
        103500
      ]
    },
    {
      "Text": "Check character status",
      "IDList": [
        105000
      ]
    },
    {
      "Text": "Select entry to execute",
      "IDList": [
        106000
      ]
    },
    {
      "Text": "Choose setting to adjust",
      "IDList": [
        106001
      ]
    },
    {
      "Text": "Change up/down camera movement",
      "IDList": [
        110001
      ]
    },
    {
      "Text": "Change left/right camera movement",
      "IDList": [
        110002
      ]
    },
    {
      "Text": "Camera reset also resets the camera y-axis",
      "IDList": [
        110003
      ]
    },
    {
      "Text": "Set camera movement speed",
      "IDList": [
        110004
      ]
    },
    {
      "Text": "Set auto lock-on to new target when former target dies",
      "IDList": [
        110005
      ]
    },
    {
      "Text": "Automatically target an enemy when attacking with no lock",
      "IDList": [
        110006
      ]
    },
    {
      "Text": "Set whether the camera automatically avoids walls",
      "IDList": [
        110007
      ]
    },
    {
      "Text": "Set controls used for jumping",
      "IDList": [
        110009
      ]
    },
    {
      "Text": "Allows for manual control of aiming of large weapons when locked-on",
      "IDList": [
        110010
      ]
    },
    {
      "Text": "Decide whether to prioritize visual quality or frame rate",
      "IDList": [
        110020
      ]
    },
    {
      "Text": "Enable/disable ray tracing",
      "IDList": [
        110021
      ]
    },
    {
      "Text": "Switch depiction of blood on or off, or set to mild",
      "IDList": [
        110101
      ]
    },
    {
      "Text": "Switch in-game subtitles on or off",
      "IDList": [
        110102
      ]
    },
    {
      "Text": "Configure how in-game HUD is displayed",
      "IDList": [
        110103
      ]
    },
    {
      "Text": "Configure cinematic effects used during special attacks",
      "IDList": [
        110104
      ]
    },
    {
      "Text": "Adjust music level",
      "IDList": [
        110105
      ]
    },
    {
      "Text": "Adjust sound effect level",
      "IDList": [
        110106
      ]
    },
    {
      "Text": "Adjust voice level",
      "IDList": [
        110107
      ]
    },
    {
      "Text": "Set overall audio volume",
      "IDList": [
        110117
      ]
    },
    {
      "Text": "Set automatic camera rotation for left/right movement",
      "IDList": [
        110118
      ]
    },
    {
      "Text": "Adjust screen brightness",
      "IDList": [
        110201
      ]
    },
    {
      "Text": "Adjust image quality when HDR is enabled",
      "IDList": [
        110202
      ]
    },
    {
      "Text": "Enable/disable HDR",
      "IDList": [
        110209
      ]
    },
    {
      "Text": "Allow or restrict voice chat",
      "IDList": [
        110301
      ]
    },
    {
      "Text": "Allow or restrict cross-region matching",
      "IDList": [
        110302
      ]
    },
    {
      "Text": "Edit to match with players using the same password",
      "IDList": [
        110303
      ]
    },
    {
      "Text": "Choose whether or not to display other players\u0027 names",
      "IDList": [
        110304
      ]
    },
    {
      "Text": "Choose whether to launch the game in online or offline mode",
      "IDList": [
        110305
      ]
    },
    {
      "Text": "Block your summon sign in worlds with adversaries present",
      "IDList": [
        110306
      ]
    },
    {
      "Text": "Review and update your consent to the data usage agreement",
      "IDList": [
        110307
      ]
    },
    {
      "Text": "Save the game and return to title menu",
      "IDList": [
        110500
      ]
    },
    {
      "Text": "Save the game and return to the desktop",
      "IDList": [
        110501
      ]
    },
    {
      "Text": "View controls",
      "IDList": [
        110900
      ]
    },
    {
      "Text": "Set keys to assign to actions",
      "IDList": [
        111006
      ]
    },
    {
      "Text": "Set device for on-screen prompts",
      "IDList": [
        111010
      ]
    },
    {
      "Text": "Set whether tutorials will be shown or not",
      "IDList": [
        111011
      ]
    },
    {
      "Text": "Set mouse sensitivity for camera movement",
      "IDList": [
        111020
      ]
    },
    {
      "Text": "Set horizontal camera controls with the mouse",
      "IDList": [
        111022
      ]
    },
    {
      "Text": "Set vertical camera controls with the mouse",
      "IDList": [
        111023
      ]
    },
    {
      "Text": "Set the screen mode in which to launch the game",
      "IDList": [
        111110
      ]
    },
    {
      "Text": "Set the resolution",
      "IDList": [
        111111
      ]
    },
    {
      "Text": "Set whether to simplify rendering in the case of reduced performance",
      "IDList": [
        111112
      ]
    },
    {
      "Text": "Set graphics quality",
      "IDList": [
        111113
      ]
    },
    {
      "Text": "Set advanced graphics quality",
      "IDList": [
        111114
      ]
    },
    {
      "Text": "Set texture quality",
      "IDList": [
        111210
      ]
    },
    {
      "Text": "Select antialiasing quality",
      "IDList": [
        111211
      ]
    },
    {
      "Text": "Select SSAO quality",
      "IDList": [
        111212
      ]
    },
    {
      "Text": "Select DOF quality",
      "IDList": [
        111213
      ]
    },
    {
      "Text": "Select motion blur quality",
      "IDList": [
        111214
      ]
    },
    {
      "Text": "Select shadow quality",
      "IDList": [
        111215
      ]
    },
    {
      "Text": "Select lighting quality",
      "IDList": [
        111216
      ]
    },
    {
      "Text": "Select effects quality",
      "IDList": [
        111217
      ]
    },
    {
      "Text": "Select volumetric quality",
      "IDList": [
        111218
      ]
    },
    {
      "Text": "Select reflection quality",
      "IDList": [
        111219
      ]
    },
    {
      "Text": "Select water surface quality",
      "IDList": [
        111220
      ]
    },
    {
      "Text": "Select shader quality",
      "IDList": [
        111221
      ]
    },
    {
      "Text": "Select ray tracing quality",
      "IDList": [
        111222
      ]
    },
    {
      "Text": "Select global illumination quality",
      "IDList": [
        111223
      ]
    },
    {
      "Text": "Select grass quality",
      "IDList": [
        111224
      ]
    },
    {
      "Text": "Choose attribute to level up",
      "IDList": [
        212000,
        212750
      ]
    },
    {
      "Text": "Spending runes to level up",
      "IDList": [
        212001
      ]
    },
    {
      "Text": "Reset attributes with rebirth",
      "IDList": [
        212751
      ]
    },
    {
      "Text": "Select an armament to enhance with Ashes of War",
      "IDList": [
        214000
      ]
    },
    {
      "Text": "Select an Ash of War to apply",
      "IDList": [
        214001
      ]
    },
    {
      "Text": "Select an affinity to grant to this armament",
      "IDList": [
        214002
      ]
    },
    {
      "Text": "Select a slot to hold a Great Rune",
      "IDList": [
        215000
      ]
    },
    {
      "Text": "Select a Great Rune to hold",
      "IDList": [
        215001
      ]
    },
    {
      "Text": "Select ashes to strengthen",
      "IDList": [
        216000
      ]
    },
    {
      "Text": "Select an armament to strengthen",
      "IDList": [
        221000,
        221010
      ]
    },
    {
      "Text": "Select memory slot",
      "IDList": [
        222000
      ]
    },
    {
      "Text": "Select sorcery/incantation to memorize",
      "IDList": [
        222001
      ]
    },
    {
      "Text": "Choose which dragon ability to make thine own",
      "IDList": [
        225000
      ]
    },
    {
      "Text": "Select puppet to obtain",
      "IDList": [
        226000,
        230000
      ]
    },
    {
      "Text": "Select Ashes of War to duplicate",
      "IDList": [
        227000
      ]
    },
    {
      "Text": "Select remembrance to duplicate",
      "IDList": [
        230100
      ]
    },
    {
      "Text": "Select item to purchase",
      "IDList": [
        231000
      ]
    },
    {
      "Text": "Select equipment of champions to receive",
      "IDList": [
        231500
      ]
    },
    {
      "Text": "Select item to sell",
      "IDList": [
        232000
      ]
    },
    {
      "Text": "Select item to craft",
      "IDList": [
        236000
      ]
    },
    {
      "Text": "Select which remembrance to plumb for power",
      "IDList": [
        236200
      ]
    },
    {
      "Text": "Select power to draw from remembrance",
      "IDList": [
        236201
      ]
    },
    {
      "Text": "Select garment to alter",
      "IDList": [
        236400
      ]
    },
    {
      "Text": "Select garment after alterations",
      "IDList": [
        236401
      ]
    },
    {
      "Text": "Select mixture slot",
      "IDList": [
        238000
      ]
    },
    {
      "Text": "Select crystal tear to mix",
      "IDList": [
        238001
      ]
    },
    {
      "Text": "View map",
      "IDList": [
        241000
      ]
    },
    {
      "Text": "Set marker",
      "IDList": [
        241100
      ]
    },
    {
      "Text": "Remove marker",
      "IDList": [
        241101
      ]
    },
    {
      "Text": "Remove all markers",
      "IDList": [
        241102
      ]
    },
    {
      "Text": "Select the site of grace where you wish to go",
      "IDList": [
        241200,
        241300
      ]
    },
    {
      "Text": "Select item to store in chest",
      "IDList": [
        251000
      ]
    },
    {
      "Text": "Select item to take from chest",
      "IDList": [
        251001
      ]
    },
    {
      "Text": "Select which action to assign",
      "IDList": [
        280005
      ]
    },
    {
      "Text": "Press the key you want to assign to this action",
      "IDList": [
        280011
      ]
    },
    {
      "Text": "Press while moving to walk",
      "IDList": [
        280100
      ]
    },
    {
      "Text": "Move forwards",
      "IDList": [
        280101
      ]
    },
    {
      "Text": "Move to the rear",
      "IDList": [
        280102
      ]
    },
    {
      "Text": "Move to the left",
      "IDList": [
        280103
      ]
    },
    {
      "Text": "Move to the right",
      "IDList": [
        280104
      ]
    },
    {
      "Text": "Press while standing still to backstep.\nPress while moving for a dodge roll, or hold to dash.",
      "IDList": [
        280105
      ]
    },
    {
      "Text": "Jump",
      "IDList": [
        280106
      ]
    },
    {
      "Text": "Switch between standing and crouching",
      "IDList": [
        280107
      ]
    },
    {
      "Text": "Move the camera up.\nChange target upwards during lock-on.",
      "IDList": [
        280200
      ]
    },
    {
      "Text": "Move the camera down.\nChange target downwards during lock-on.",
      "IDList": [
        280201
      ]
    },
    {
      "Text": "Move the camera to the left.\nChange target to the left during lock-on.",
      "IDList": [
        280202
      ]
    },
    {
      "Text": "Move the camera to the right.\nChange target to the right during lock-on.",
      "IDList": [
        280203
      ]
    },
    {
      "Text": "Reset the camera\u0027s position.\nTurn lock-on fixation on or off during lock-on.",
      "IDList": [
        280204
      ]
    },
    {
      "Text": "Change your Quick Item",
      "IDList": [
        280300
      ]
    },
    {
      "Text": "Change your right-hand armament",
      "IDList": [
        280301
      ]
    },
    {
      "Text": "Change your left-hand armament",
      "IDList": [
        280302
      ]
    },
    {
      "Text": "Change your selected sorcery or incantation",
      "IDList": [
        280303
      ]
    },
    {
      "Text": "Normal attack with your right-hand armament",
      "IDList": [
        280400
      ]
    },
    {
      "Text": "Strong attack with your right-hand armament. Hold to charge the attack.",
      "IDList": [
        280401
      ]
    },
    {
      "Text": "Guard with your left-hand armament",
      "IDList": [
        280402
      ]
    },
    {
      "Text": "Perform a skill",
      "IDList": [
        280403
      ]
    },
    {
      "Text": "Perform various actions",
      "IDList": [
        280404
      ]
    },
    {
      "Text": "Use an item",
      "IDList": [
        280405
      ]
    },
    {
      "Text": "Wield your right-hand armament in both hands.\nHold to wield your left-hand armament in both hands instead.",
      "IDList": [
        280406
      ]
    },
    {
      "Text": "Select which character to use",
      "IDList": [
        288000
      ]
    },
    {
      "Text": "Select a base for creating your character",
      "IDList": [
        288001
      ]
    },
    {
      "Text": "Enter name",
      "IDList": [
        291000
      ]
    },
    {
      "Text": "Select body type",
      "IDList": [
        291001
      ]
    },
    {
      "Text": "Select apparent age",
      "IDList": [
        291002
      ]
    },
    {
      "Text": "Select voice",
      "IDList": [
        291003
      ]
    },
    {
      "Text": "Select origin",
      "IDList": [
        291010
      ]
    },
    {
      "Text": "Select keepsake",
      "IDList": [
        291011
      ]
    },
    {
      "Text": "Choose a template appearance",
      "IDList": [
        291020
      ]
    },
    {
      "Text": "Alter facial features",
      "IDList": [
        291021
      ]
    },
    {
      "Text": "Alter general figure",
      "IDList": [
        291022
      ]
    },
    {
      "Text": "Alter skin color and details",
      "IDList": [
        291023
      ]
    },
    {
      "Text": "Edit details of character appearance",
      "IDList": [
        291025
      ]
    },
    {
      "Text": "Save present settings as a favorite",
      "IDList": [
        291030
      ]
    },
    {
      "Text": "Load saved favorite",
      "IDList": [
        291031
      ]
    },
    {
      "Text": "Finalize character",
      "IDList": [
        291050
      ]
    },
    {
      "Text": "Start over with a new appearance",
      "IDList": [
        291051,
        291052
      ]
    },
    {
      "Text": "Edit character\u0027s facial features",
      "IDList": [
        292000
      ]
    },
    {
      "Text": "Edit character\u0027s facial shape",
      "IDList": [
        292001
      ]
    },
    {
      "Text": "Edit character\u0027s hair",
      "IDList": [
        292010
      ]
    },
    {
      "Text": "Edit character\u0027s eyebrows",
      "IDList": [
        292011
      ]
    },
    {
      "Text": "Edit character\u0027s facial hair",
      "IDList": [
        292012
      ]
    },
    {
      "Text": "Edit character\u0027s eyelashes",
      "IDList": [
        292013
      ]
    },
    {
      "Text": "Edit character\u0027s eyes",
      "IDList": [
        292020
      ]
    },
    {
      "Text": "Edit character\u0027s skin features",
      "IDList": [
        292025
      ]
    },
    {
      "Text": "Edit character\u0027s makeup",
      "IDList": [
        292030
      ]
    },
    {
      "Text": "Edit character\u0027s tattoos/marks/eyepatch",
      "IDList": [
        292040
      ]
    },
    {
      "Text": "Select face similar to present face",
      "IDList": [
        292050
      ]
    },
    {
      "Text": "Adjust character\u0027s head",
      "IDList": [
        292060
      ]
    },
    {
      "Text": "Adjust character\u0027s chest",
      "IDList": [
        292061
      ]
    },
    {
      "Text": "Adjust character\u0027s abdomen",
      "IDList": [
        292062
      ]
    },
    {
      "Text": "Adjust character\u0027s arms",
      "IDList": [
        292063
      ]
    },
    {
      "Text": "Adjust character\u0027s legs",
      "IDList": [
        292064
      ]
    },
    {
      "Text": "Adjust character\u0027s body hair",
      "IDList": [
        292070
      ]
    },
    {
      "Text": "Adjust character\u0027s body hair color",
      "IDList": [
        292071
      ]
    },
    {
      "Text": "Select musculature",
      "IDList": [
        292072
      ]
    },
    {
      "Text": "Set whether to display burn marks",
      "IDList": [
        292080
      ]
    },
    {
      "Text": "Choose bone structure",
      "IDList": [
        293000
      ]
    },
    {
      "Text": "Adjust facial feature strength",
      "IDList": [
        293001
      ]
    },
    {
      "Text": "Adjust apparent age",
      "IDList": [
        293002
      ]
    },
    {
      "Text": "Adjust facial aesthetic",
      "IDList": [
        293003
      ]
    },
    {
      "Text": "Edit facial balance",
      "IDList": [
        293010
      ]
    },
    {
      "Text": "Edit forehead and glabella",
      "IDList": [
        293011
      ]
    },
    {
      "Text": "Edit brow ridge",
      "IDList": [
        293012
      ]
    },
    {
      "Text": "Edit eyes",
      "IDList": [
        293013
      ]
    },
    {
      "Text": "Edit nose ridge",
      "IDList": [
        293014
      ]
    },
    {
      "Text": "Edit nostrils",
      "IDList": [
        293015
      ]
    },
    {
      "Text": "Edit cheeks",
      "IDList": [
        293016
      ]
    },
    {
      "Text": "Edit lips",
      "IDList": [
        293017
      ]
    },
    {
      "Text": "Edit mouth",
      "IDList": [
        293018
      ]
    },
    {
      "Text": "Edit chin",
      "IDList": [
        293019
      ]
    },
    {
      "Text": "Edit jaw",
      "IDList": [
        293020
      ]
    },
    {
      "Text": "Select hair style",
      "IDList": [
        293100
      ]
    },
    {
      "Text": "Edit hair color",
      "IDList": [
        293101
      ]
    },
    {
      "Text": "Adjust hair luster",
      "IDList": [
        293102
      ]
    },
    {
      "Text": "Adjust hair root darkness",
      "IDList": [
        293103
      ]
    },
    {
      "Text": "Adjust quantity of white hairs",
      "IDList": [
        293104
      ]
    },
    {
      "Text": "Select brow shape",
      "IDList": [
        293110
      ]
    },
    {
      "Text": "Edit brow color",
      "IDList": [
        293111
      ]
    },
    {
      "Text": "Adjust eyebrow luster",
      "IDList": [
        293112
      ]
    },
    {
      "Text": "Adjust eyebrow root darkness",
      "IDList": [
        293113
      ]
    },
    {
      "Text": "Adjust quantity of white eyebrow hairs",
      "IDList": [
        293114
      ]
    },
    {
      "Text": "Select beard type",
      "IDList": [
        293120
      ]
    },
    {
      "Text": "Edit beard color",
      "IDList": [
        293121
      ]
    },
    {
      "Text": "Adjust facial hair luster",
      "IDList": [
        293122
      ]
    },
    {
      "Text": "Adjust facial hair root darkness",
      "IDList": [
        293123
      ]
    },
    {
      "Text": "Adjust quantity of white facial hair",
      "IDList": [
        293124
      ]
    },
    {
      "Text": "Adjust stubble thickness",
      "IDList": [
        293125
      ]
    },
    {
      "Text": "Select eyelash shape",
      "IDList": [
        293130
      ]
    },
    {
      "Text": "Edit eyelash color",
      "IDList": [
        293131
      ]
    },
    {
      "Text": "Adjust right eye size",
      "IDList": [
        293140
      ]
    },
    {
      "Text": "Edit color of right iris",
      "IDList": [
        293141
      ]
    },
    {
      "Text": "Adjust opacity of right eye clouding",
      "IDList": [
        293142
      ]
    },
    {
      "Text": "Adjust color of right eye clouding",
      "IDList": [
        293143
      ]
    },
    {
      "Text": "Adjust color of right eye white",
      "IDList": [
        293144
      ]
    },
    {
      "Text": "Adjust right eye\u0027s distance from the center of the face",
      "IDList": [
        293145
      ]
    },
    {
      "Text": "Adjust left eye size",
      "IDList": [
        293150
      ]
    },
    {
      "Text": "Edit color of left iris",
      "IDList": [
        293151
      ]
    },
    {
      "Text": "Adjust opacity of left eye clouding",
      "IDList": [
        293152
      ]
    },
    {
      "Text": "Adjust color of left eye clouding",
      "IDList": [
        293153
      ]
    },
    {
      "Text": "Adjust color of left eye white",
      "IDList": [
        293154
      ]
    },
    {
      "Text": "Adjust left eye\u0027s distance from the center of the face",
      "IDList": [
        293155
      ]
    },
    {
      "Text": "Apply eye alterations",
      "IDList": [
        293156,
        297185
      ]
    },
    {
      "Text": "Alter visibility of pores",
      "IDList": [
        293160
      ]
    },
    {
      "Text": "Adjust skin luster",
      "IDList": [
        293161
      ]
    },
    {
      "Text": "Adjust darkness of bags under eyes",
      "IDList": [
        293162
      ]
    },
    {
      "Text": "Adjust the color of bags under eyes",
      "IDList": [
        293163
      ]
    },
    {
      "Text": "Adjust cheek makeup intensity",
      "IDList": [
        293164
      ]
    },
    {
      "Text": "Adjust cheek color",
      "IDList": [
        293165
      ]
    },
    {
      "Text": "Adjust eyeliner darkness",
      "IDList": [
        293166
      ]
    },
    {
      "Text": "Adjust eyeliner color",
      "IDList": [
        293167
      ]
    },
    {
      "Text": "Adjust eyeshadow darkness on upper eyelid",
      "IDList": [
        293168
      ]
    },
    {
      "Text": "Adjust eyeshadow color on upper eyelid",
      "IDList": [
        293169
      ]
    },
    {
      "Text": "Adjust eyeshadow darkness on lower eyelid",
      "IDList": [
        293170
      ]
    },
    {
      "Text": "Adjust eyeshadow color on lower eyelid",
      "IDList": [
        293171
      ]
    },
    {
      "Text": "Adjust lipstick intensity",
      "IDList": [
        293172
      ]
    },
    {
      "Text": "Adjust lipstick color",
      "IDList": [
        293173
      ]
    },
    {
      "Text": "Select appearance of tattoo/mark",
      "IDList": [
        293180
      ]
    },
    {
      "Text": "Edit tattoo/mark color",
      "IDList": [
        293181
      ]
    },
    {
      "Text": "Adjust position of tattoo/mark",
      "IDList": [
        293182
      ]
    },
    {
      "Text": "Choose an eyepatch",
      "IDList": [
        293190
      ]
    },
    {
      "Text": "Adjust eyepatch color",
      "IDList": [
        293191
      ]
    },
    {
      "Text": "Buff body\nBody type has no bearing on ability",
      "IDList": [
        297100
      ]
    },
    {
      "Text": "Slender body\nBody type has no bearing on ability",
      "IDList": [
        297101
      ]
    },
    {
      "Text": "Young\nAge only affects appearance,\nhas no bearing on ability",
      "IDList": [
        297110
      ]
    },
    {
      "Text": "Mature\nAge only affects appearance,\nhas no bearing on ability",
      "IDList": [
        297111
      ]
    },
    {
      "Text": "Aged\nAge only affects appearance,\nhas no bearing on ability",
      "IDList": [
        297112
      ]
    },
    {
      "Text": "Young voice type 1",
      "IDList": [
        297120
      ]
    },
    {
      "Text": "Mature voice type 1",
      "IDList": [
        297121
      ]
    },
    {
      "Text": "Aged voice type 1",
      "IDList": [
        297122
      ]
    },
    {
      "Text": "Young voice type 2",
      "IDList": [
        297125
      ]
    },
    {
      "Text": "Mature voice type 2",
      "IDList": [
        297126
      ]
    },
    {
      "Text": "Aged voice type 2",
      "IDList": [
        297127
      ]
    },
    {
      "Text": "A knight exiled from their homeland to\nwander. A solid, armor-clad origin.",
      "IDList": [
        297130
      ]
    },
    {
      "Text": "A nomad warrior who fights wielding two\nblades at once. An origin of exceptional\ntechnique.",
      "IDList": [
        297131
      ]
    },
    {
      "Text": "A stalwart hero, at home with a battleaxe,\ndescended from a badlands chieftain.",
      "IDList": [
        297132
      ]
    },
    {
      "Text": "A dangerous bandit who strikes for\nweak points. Excels at ranged combat\nwith bows.",
      "IDList": [
        297133
      ]
    },
    {
      "Text": "A scholar who reads fate in the stars.\nHeir to the school of glintstone sorcery.",
      "IDList": [
        297134
      ]
    },
    {
      "Text": "A seer ostracized for inauspicious\nprophecies. Well-versed in healing\nincantations.",
      "IDList": [
        297135
      ]
    },
    {
      "Text": "A capable fighter from the distant Land of\nReeds. Handy with katana and longbows.",
      "IDList": [
        297136
      ]
    },
    {
      "Text": "A prisoner bound in an iron mask. Studied\nin glintstone sorcery, having lived among\nthe elite prior to sentencing.",
      "IDList": [
        297137
      ]
    },
    {
      "Text": "A church spy adept at covert operations.\nEqually adept with a sword as they are\nwith their incantations.",
      "IDList": [
        297138
      ]
    },
    {
      "Text": "A poor, purposeless sod, naked as the day\nthey were born. A nice club is all they have.",
      "IDList": [
        297139
      ]
    },
    {
      "Text": "No keepsake. The past has been well and\ntruly left behind.",
      "IDList": [
        297150
      ]
    },
    {
      "Text": "A medallion inlaid with crimson amber.\nIncreases maximum HP.",
      "IDList": [
        297151
      ]
    },
    {
      "Text": "The gold of grace shining in the eyes of\nthe people of the Lands Between.\nUse to gain many runes.",
      "IDList": [
        297152
      ]
    },
    {
      "Text": "A golden seed washed ashore from the\nLands Between. Said to enhance\nSacred Flasks.",
      "IDList": [
        297153
      ]
    },
    {
      "Text": "The ashes of small, diminutive golems.\nAshes are said to hold spirits within.",
      "IDList": [
        297154
      ]
    },
    {
      "Text": "Three strange cracked pots that somehow\nmend themselves. A container for certain\nthrown items.",
      "IDList": [
        297156
      ]
    },
    {
      "Text": "Two stone keys shaped like swords.\nBreaks the seal on imp statues,\nbut can only be used once.",
      "IDList": [
        297157
      ]
    },
    {
      "Text": "Five sacred branches charged with beguiling\npower. Said to originate from the\ndemigod Miquella.",
      "IDList": [
        297158
      ]
    },
    {
      "Text": "Five pieces of boiled prawn.\nBoosts physical damage negation.",
      "IDList": [
        297159
      ]
    },
    {
      "Text": "The crazed likeness of a noble whose\neyes have been gouged out.\nAttracts enemies\u0027 aggression.",
      "IDList": [
        297160
      ]
    },
    {
      "Text": "Average physique",
      "IDList": [
        297170
      ]
    },
    {
      "Text": "Muscular physique",
      "IDList": [
        297171
      ]
    },
    {
      "Text": "Mirror tattoos and marks",
      "IDList": [
        297180
      ]
    },
    {
      "Text": "Do not mirror tattoos and marks",
      "IDList": [
        297181
      ]
    },
    {
      "Text": "Do not apply eye alterations",
      "IDList": [
        297186
      ]
    },
    {
      "Text": "Display burn marks",
      "IDList": [
        297187
      ]
    },
    {
      "Text": "Do not display burn marks",
      "IDList": [
        297188
      ]
    },
    {
      "Text": "The most common face among the Tarnished.\nAfter all, they were all warriors once.",
      "IDList": [
        297200,
        297220
      ]
    },
    {
      "Text": "The face of an austere pilgrim.\nThere are many roads to truth.",
      "IDList": [
        297201,
        297221
      ]
    },
    {
      "Text": "A regal face found among those who claim\nnoble blood in the Lands Between.",
      "IDList": [
        297202,
        297222
      ]
    },
    {
      "Text": "Face found among a proud and seclusive\ntribe of folk well-versed in ancient\nlegends and heresies alike.",
      "IDList": [
        297203,
        297223
      ]
    },
    {
      "Text": "A face found among the hardy people\nof the unforgiving north. Some say\nthey\u0027re descended from giants.",
      "IDList": [
        297204,
        297224
      ]
    },
    {
      "Text": "The face of one who wanders the seas in\nsearch of their home in the Lands Between.",
      "IDList": [
        297205,
        297225
      ]
    },
    {
      "Text": "A face from the faraway, isolated Land\nof Reeds, where blood is a familiar sight.",
      "IDList": [
        297206,
        297226
      ]
    },
    {
      "Text": "The stony face of the people of the\nancient dragons, among whom life\nis typically short.",
      "IDList": [
        297207,
        297227
      ]
    },
    {
      "Text": "The features of those known as\nNightfolk. Few in number, they were\nsaid to bleed silver long ago.",
      "IDList": [
        297208,
        297228
      ]
    },
    {
      "Text": "The face of the Numen, supposed\ndescendants of denizens of another\nworld. Long-lived but seldom born.",
      "IDList": [
        297209,
        297229
      ]
    },
    {
      "Text": "Select gesture for this slot",
      "IDList": [
        301000
      ]
    },
    {
      "Text": "Select gesture to use",
      "IDList": [
        301001
      ]
    },
    {
      "Text": "Edit message composition",
      "IDList": [
        321000
      ]
    },
    {
      "Text": "Change bound gesture",
      "IDList": [
        321001,
        321004
      ]
    },
    {
      "Text": "Finish writing message",
      "IDList": [
        321002
      ]
    },
    {
      "Text": "Select template",
      "IDList": [
        321003,
        321006
      ]
    },
    {
      "Text": "Select word category",
      "IDList": [
        321005
      ]
    },
    {
      "Text": "Select word",
      "IDList": [
        321007
      ]
    },
    {
      "Text": "Select conjunction",
      "IDList": [
        321008
      ]
    },
    {
      "Text": "View composed messages",
      "IDList": [
        322000
      ]
    },
    {
      "Text": "See recently viewed messages",
      "IDList": [
        324000
      ]
    },
    {
      "Text": "Select profile to load",
      "IDList": [
        406000
      ]
    },
    {
      "Text": "Select profile to delete",
      "IDList": [
        406001
      ]
    },
    {
      "Text": "Select combat format",
      "IDList": [
        506000
      ]
    },
    {
      "Text": "Select combat venue",
      "IDList": [
        506001
      ]
    },
    {
      "Text": "Edit Colosseum Password to be matched with players using the same password",
      "IDList": [
        506002
      ]
    },
    {
      "Text": "Enter Colosseum combat and begin matchmaking",
      "IDList": [
        506003
      ]
    },
    {
      "Text": "Cancel matchmaking",
      "IDList": [
        506004
      ]
    },
    {
      "Text": "Choose preferred team to join in United Combat\u2014Colosseum Password settings must be the same for all players.",
      "IDList": [
        506005
      ]
    },
    {
      "Text": "Set custom rules for Colosseum password matchmaking. Can be accessed once Colosseum Password is set.",
      "IDList": [
        506006
      ]
    },
    {
      "Text": "Choose number of combatants in Colosseum",
      "IDList": [
        506007
      ]
    },
    {
      "Text": "Choose whether or not to allow spirit ashes",
      "IDList": [
        506008
      ]
    }
  ]
}